examples/__init__.py
examples/chat_bot.py
examples/desktop_authenticator.py
examples/storehouse.py
pysteam/__init__.py
pysteam/chat.py
pysteam/client.py
pysteam/confirmation.py
pysteam/exceptions.py
pysteam/guard.py
pysteam/login.py
pysteam/market.py
pysteam/models.py
pysteam/utils.py
steampy/__init__.py
steampy/chat.py
steampy/client.py
steampy/confirmation.py
steampy/exceptions.py
steampy/guard.py
steampy/login.py
steampy/market.py
steampy/models.py
steampy/utils.py
test/__init__.py
test/test_client.py
test/test_guard.py
test/test_market.py
test/test_utils.py
pepper_steam-0.74.1.dist-info/LICENSE.txt
pepper_steam-0.74.1.dist-info/METADATA
pepper_steam-0.74.1.dist-info/WHEEL
pepper_steam-0.74.1.dist-info/top_level.txt
pepper_steam-0.74.1.dist-info/RECORD
